PyCypher/Cy.py
PyCypher/__init__.py
pycypherlib-1.4.2.dist-info/licenses/LICENSE
pycypherlib-1.4.2.dist-info/METADATA
pycypherlib-1.4.2.dist-info/WHEEL
pycypherlib-1.4.2.dist-info/top_level.txt
pycypherlib-1.4.2.dist-info/RECORD
