Metadata-Version: 2.4
Name: PyCypherLib
Version: 1.4.2
Summary: Secure file encryption and decryption library with fluent API
Author-email: eaannist <eaannist@gmail.com>
License-Expression: MIT
Project-URL: Homepage, https://github.com/eaannist/PyCypher
Project-URL: Repository, https://github.com/eaannist/PyCypher
Project-URL: Issues, https://github.com/eaannist/PyCypher/issues
Classifier: Development Status :: 4 - Beta
Classifier: Intended Audience :: Developers
Classifier: Operating System :: OS Independent
Classifier: Programming Language :: Python :: 3
Classifier: Topic :: Security :: Cryptography
Requires-Python: >=3.10
License-File: LICENSE
Requires-Dist: cryptography>=3.0.0
Requires-Dist: argon2-cffi>=21.0.0
Dynamic: license-file
